{
    "josh-house-katie-thanksgiving": {
        "name": "Friendsgiving",
        "photos": [
            {
                "src": "https://drive.google.com/file/d/1pk10r3_5vOhIOWGA2-D2vREUUO7WXQ7g/view?usp=drive_link",
                "alt": "no alt"
            },
            {
                "src": "https://drive.google.com/file/d/1jNXz0AlfpPz0inqTOAq-4c2JywPSW3B1/view?usp=drive_link",
                "alt": "no alt"
            },
            {
                "src": "https://drive.google.com/file/d/1xxGkyoWXz_qX2CpVkv-MLmGw4yucQV5w/view?usp=drive_link",
                "alt": "no alt"
            },
            {
                "src": "https://drive.google.com/file/d/1Sde2JvlcMfm4yoZE8c7uq4NjwrGrhRs0/view?usp=drive_link",
                "alt": "no alt"
            },
            {
                "src": "https://drive.google.com/file/d/1XZ5tpEGiDjHyAVYPMLt3F0V8EY0y9k9d/view?usp=drive_link",
                "alt": "no alt"
            },
            {
                "src": "https://drive.google.com/file/d/1ca2lVa2g7fOZKiBo427jKWEL-o1Ktah6/view?usp=drive_link",
                "alt": "no alt"
            },
            {
                "src": "https://drive.google.com/file/d/1GSgCM53tKbkXj_slmtDn3uzqpe2u1A8v/view?usp=drive_link",
                "alt": "no alt"
            },
            {
                "src": "https://drive.google.com/file/d/1KyKwYUJHJHPUpi6FGCGR10NdlA_b10tf/view?usp=drive_link",
                "alt": "no alt"
            },
            {
                "src": "https://drive.google.com/file/d/1o7flSPEhkJG8Fz4T7cVFEtJr3fUZjg4u/view?usp=drive_link",
                "alt": "no alt"
            },
            {
                "src": "https://drive.google.com/file/d/1niDfUj2faL1Pq94EJv_Jevm8CdT3KR8H/view?usp=drive_link",
                "alt": "no alt"
            },
            {
                "src": "https://drive.google.com/file/d/1VSHv4ImMRcB4Tpbc-iVGk1_nq79kS4-3/view?usp=drive_link",
                "alt": "no alt"
            },
            {
                "src": "https://drive.google.com/file/d/1gX8D_JbfZG1r9H8iYl29pFXyzC1cgoq6/view?usp=drive_link",
                "alt": "no alt"
            },
            {
                "src": "https://drive.google.com/file/d/13QBokSkYEA67eYlruvd4Mim5s3zsXGxO/view?usp=drive_link",
                "alt": "no alt"
            },
            {
                "src": "https://drive.google.com/file/d/1KIYrFGmkJIga3G3pBswoSrzPo902gtOL/view?usp=drive_link",
                "alt": "no alt"
            },
            {
                "src": "https://drive.google.com/file/d/1O5-Mq7GgRJjlwUP9G8Aa-6iMaVet78Ai/view?usp=drive_link",
                "alt": "no alt"
            },
            {
                "src": "https://drive.google.com/file/d/1flkv59O1thzrk9KgUAC5PIe1VoPoDYjU/view?usp=drive_link",
                "alt": "no alt"
            },
            {
                "src": "https://drive.google.com/file/d/1J4YhOO5VktDg7nu_RfG-AGH7bdpHxgO8/view?usp=drive_link",
                "alt": "no alt"
            },
            {
                "src": "https://drive.google.com/file/d/1teIacu6a4QD5SVsnji_UBLTwz6S_Nyij/view?usp=drive_link",
                "alt": "no alt"
            },
            {
                "src": "https://drive.google.com/file/d/1D9pgd2EIURxiI6MOFwJKsnoAF6JIhksG/view?usp=drive_link",
                "alt": "no alt"
            },
            {
                "src": "https://drive.google.com/file/d/1d__niTej978lNbqEPOfbkmbFOhgrOYiw/view?usp=drive_link",
                "alt": "no alt"
            },
            {
                "src": "https://drive.google.com/file/d/1jETURog460hkOwVCL0dxViZVmNg5L-pJ/view?usp=drive_link",
                "alt": "no alt"
            },
            {
                "src": "https://drive.google.com/file/d/1VeOXvA0Bc13yB50DeV6qUHQX7IiOjvyB/view?usp=drive_link",
                "alt": "no alt"
            },
            {
                "src": "https://drive.google.com/file/d/108l817-k4i90Tik325_um2iPkMu58NMj/view?usp=drive_link",
                "alt": "no alt"
            },
            {
                "src": "https://drive.google.com/file/d/1_PS9BGuWq6m6_yW3FF_ZKpKfTD5iqls6/view?usp=drive_link",
                "alt": "no alt"
            },
            {
                "src": "https://drive.google.com/file/d/167fqXp_0QSslV5q3mnQISoVoIzGHRrE4/view?usp=drive_link",
                "alt": "no alt"
            },
            {
                "src": "https://drive.google.com/file/d/1XSc0nKSDtpYG0zd08EEl4copoXCpFojE/view?usp=drive_link",
                "alt": "no alt"
            },
            {
                "src": "https://drive.google.com/file/d/1vh79riLWG1kDQUB7EWMVd6vDR2PKPRvX/view?usp=drive_link",
                "alt": "no alt"
            },
            {
                "src": "https://drive.google.com/file/d/1n3E_9FYE_L3SPcpXrgkZYtCb--4HQQ1i/view?usp=drive_link",
                "alt": "no alt"
            },
            {
                "src": "https://drive.google.com/file/d/1fiu1uhlhsnY81_ylzolhcvZi9ueG8cFS/view?usp=drive_link",
                "alt": "no alt"
            },
            {
                "src": "https://drive.google.com/file/d/17jefwBnUw2GCw-vGTa0ZRZnMb7EJISyX/view?usp=drive_link",
                "alt": "no alt"
            },
            {
                "src": "https://drive.google.com/file/d/1j-VLyE9-rv9pqbkc5Gm8qhYs83ZVCfae/view?usp=drive_link",
                "alt": "no alt"
            },
            {
                "src": "https://drive.google.com/file/d/1zu7as4RUwjDP0TNv8xyt9y-4eVOgLt7C/view?usp=drive_link",
                "alt": "no alt"
            },
            {
                "src": "https://drive.google.com/file/d/1SiasZj2stY76ik3jP4Ff87RC3qfNOhWJ/view?usp=drive_link",
                "alt": "no alt"
            },
            {
                "src": "https://drive.google.com/file/d/1KD4iM_2c-B6iho828iEUbPWYSRI2FhrW/view?usp=drive_link",
                "alt": "no alt"
            },
            {
                "src": "https://drive.google.com/file/d/1jdKl-e7WT-c7X8hmCab_Xxmv_SbhHTAo/view?usp=drive_link",
                "alt": "no alt"
            },
            {
                "src": "https://drive.google.com/file/d/1FAHgVJIQ8OCmwZ-wx8jM4DgJNhLuM43h/view?usp=drive_link",
                "alt": "no alt"
            },
            {
                "src": "https://drive.google.com/file/d/1MMV8G4ojwVjYh27pgJOcIMys03IhO1c_/view?usp=drive_link",
                "alt": "no alt"
            },
            {
                "src": "https://drive.google.com/file/d/1xIygWIFHtSpr6ftHSNZL3e7RGJ2Df9oQ/view?usp=drive_link",
                "alt": "no alt"
            },
            {
                "src": "https://drive.google.com/file/d/1NmzzY1BuyFYdRLETVBp9wSrJ6zMN4-e9/view?usp=drive_link",
                "alt": "no alt"
            },
            {
                "src": "https://drive.google.com/file/d/1gZExggz8XmWyTQq3QcIjY-icQFP8ux2d/view?usp=drive_link",
                "alt": "no alt"
            },
            {
                "src": "https://drive.google.com/file/d/1Wg3wLPKFi_HGjEt8PodcaFzNAWtUg0Fr/view?usp=drive_link",
                "alt": "no alt"
            },
            {
                "src": "https://drive.google.com/file/d/10X9HJMUyzyBU6DE3zflxZvGnqEvf1T3_/view?usp=drive_link",
                "alt": "no alt"
            },
            {
                "src": "https://drive.google.com/file/d/16nAbJGe_ZTSKsKyoLNgkJvPwLqxSv_0T/view?usp=drive_link",
                "alt": "no alt"
            },
            {
                "src": "https://drive.google.com/file/d/10Zg-fzHe-QGEdFpuqFcknEPFG5p5DGIq/view?usp=drive_link",
                "alt": "no alt"
            },
            {
                "src": "https://drive.google.com/file/d/1hyhImIAGqHif4mkq9osI5eL4xdMhwnxX/view?usp=drive_link",
                "alt": "no alt"
            },
            {
                "src": "https://drive.google.com/file/d/1soVZ7QW97DUCqyu9NgY_jhi1GfXqM0Ww/view?usp=drive_link",
                "alt": "no alt"
            },
            {
                "src": "https://drive.google.com/file/d/1ZVs7CH8LE2_VWsn6G5UuteN2Viux7Jed/view?usp=drive_link",
                "alt": "no alt"
            },
            {
                "src": "https://drive.google.com/file/d/1OvLY_0onzQhEk73vuprrlKi4pIkgffN1/view?usp=drive_link",
                "alt": "no alt"
            },
            {
                "src": "https://drive.google.com/file/d/1VaF_O2TeRIFgmHqqgnVVA7sX1M8UvKtA/view?usp=drive_link",
                "alt": "no alt"
            },
            {
                "src": "https://drive.google.com/file/d/1EjQGbD8yFuzvdnQacwO9Qocrb8kixYSE/view?usp=drive_link",
                "alt": "no alt"
            },
            {
                "src": "https://drive.google.com/file/d/11cJ_oNpoYb6GzM7t_rctiDx7WwpDNxwN/view?usp=drive_link",
                "alt": "no alt"
            },
            {
                "src": "https://drive.google.com/file/d/1mnhC6LXys0aG0-Phhxd-m466kwM-sBBD/view?usp=drive_link",
                "alt": "no alt"
            },
            {
                "src": "https://drive.google.com/file/d/1d61CDgWT_Kbs3OApdgez4ed5BNCC-omT/view?usp=drive_link",
                "alt": "no alt"
            },
            {
                "src": "https://drive.google.com/file/d/1cpHlZunKpGGCtH20riQ2GydoR_JYvGMF/view?usp=drive_link",
                "alt": "no alt"
            },
            {
                "src": "https://drive.google.com/file/d/13yEp0KZv-fST1CghxdQzMWNWvLYtpEdX/view?usp=drive_link",
                "alt": "no alt"
            },
            {
                "src": "https://drive.google.com/file/d/1usaUHmEKxASCnXVCMsW5T3WJnn7gjjzz/view?usp=drive_link",
                "alt": "no alt"
            },
            {
                "src": "https://drive.google.com/file/d/18MjAxZB_QuOwL1ZpAVafFNS4SMEwiw2E/view?usp=drive_link",
                "alt": "no alt"
            },
            {
                "src": "https://drive.google.com/file/d/1LLkWzIhHxHBkusik4T--fbn-x4yLTBQN/view?usp=drive_link",
                "alt": "no alt"
            },
            {
                "src": "https://drive.google.com/file/d/1gx2ub0p4oLRbAOyv12GCUcTMlS7_0naD/view?usp=drive_link",
                "alt": "no alt"
            },
            {
                "src": "https://drive.google.com/file/d/1OEL7nX2ucPei6L1iIJXFcZBWiboRDjQt/view?usp=drive_link",
                "alt": "no alt"
            },
            {
                "src": "https://drive.google.com/file/d/1g4GOmulCiasrPjVTLuGJx9jyfi8sGbrN/view?usp=drive_link",
                "alt": "no alt"
            },
            {
                "src": "https://drive.google.com/file/d/1WIPiDhhOJWpTmo6bMd-r37pfRZBVdSo0/view?usp=drive_link",
                "alt": "no alt"
            },
            {
                "src": "https://drive.google.com/file/d/10h0IWpBAQi66dXfVXQ8AKVQycR7Rk98T/view?usp=drive_link",
                "alt": "no alt"
            },
            {
                "src": "https://drive.google.com/file/d/1AnM_0CQklf4PGhAWp3nUJHaBOAIbwLxS/view?usp=drive_link",
                "alt": "no alt"
            },
            {
                "src": "https://drive.google.com/file/d/1NfPi9JvSum3QURH0bVlayWKuqDhjx3Rk/view?usp=drive_link",
                "alt": "no alt"
            },
            {
                "src": "https://drive.google.com/file/d/1hsEwxKzf41e6BOQy1HqiHQcX8eyM7oIq/view?usp=drive_link",
                "alt": "no alt"
            },
            {
                "src": "https://drive.google.com/file/d/12aLCV12X6yu8HoqNOP8kn_HCR3HxSEy4/view?usp=drive_link",
                "alt": "no alt"
            },
            {
                "src": "https://drive.google.com/file/d/1rZ2d5im7M_Plriu_rjMH6SpmRUP5Sou1/view?usp=drive_link",
                "alt": "no alt"
            },
            {
                "src": "https://drive.google.com/file/d/1YfRT9gWvnWXGu9tJWYyU0-fx-7IKVXr1/view?usp=drive_link",
                "alt": "no alt"
            },
            {
                "src": "https://drive.google.com/file/d/1pE-HIZ7IMatVWp7eXhJr3EwIFMEicbis/view?usp=drive_link",
                "alt": "no alt"
            },
            {
                "src": "https://drive.google.com/file/d/16hzxzZhGeQU8jJrrmE8L8Kd8iBAiARlM/view?usp=drive_link",
                "alt": "no alt"
            },
            {
                "src": "https://drive.google.com/file/d/1lGgRlR6WN2Sj0oJpSBbasfNU3IYrxciF/view?usp=drive_link",
                "alt": "no alt"
            },
            {
                "src": "https://drive.google.com/file/d/1cyRCHje7OlB-3RIGjD3kgpTRi10_dIao/view?usp=drive_link",
                "alt": "no alt"
            },
            {
                "src": "https://drive.google.com/file/d/1Szg5IUJns_JQAA9S7YgR6h_T1QUf8HWj/view?usp=drive_link",
                "alt": "no alt"
            },
            {
                "src": "https://drive.google.com/file/d/1cmrWoqlniIjQaEU4TqtKgP8dFSChkLqF/view?usp=drive_link",
                "alt": "no alt"
            },
            {
                "src": "https://drive.google.com/file/d/1QEAjAA9fxPgM8TBwPajP8gIgVn0MaTEf/view?usp=drive_link",
                "alt": "no alt"
            },
            {
                "src": "https://drive.google.com/file/d/1ftEGVWxWFKNaLrs2s1F5_grmuCvIlBOG/view?usp=drive_link",
                "alt": "no alt"
            },
            {
                "src": "https://drive.google.com/file/d/1gOk44qB6ASLwyxuj92-InqT-44pS3Isi/view?usp=drive_link",
                "alt": "no alt"
            },
            {
                "src": "https://drive.google.com/file/d/1Z-oztbJyMH-BU5ogbcfCs4ZFBJO6aXPA/view?usp=drive_link",
                "alt": "no alt"
            },
            {
                "src": "https://drive.google.com/file/d/1cz-kdlkUWTir_njZi77uUNW7MxsJ5l0m/view?usp=drive_link",
                "alt": "no alt"
            },
            {
                "src": "https://drive.google.com/file/d/1crGNxB1dtPKqD1OXjO-69gAvljVjhZr8/view?usp=drive_link",
                "alt": "no alt"
            },
            {
                "src": "https://drive.google.com/file/d/1twsKwVkZPygI-PDxFgeJhUD617LEFPYx/view?usp=drive_link",
                "alt": "no alt"
            },
            {
                "src": "https://drive.google.com/file/d/1GQTrrUTCRuLlUQ1vHENRxsbSzsewkdO0/view?usp=drive_link",
                "alt": "no alt"
            },
            {
                "src": "https://drive.google.com/file/d/1hb2UXrqL2sdd4LvJs8O8AgZ-L4sCOIlO/view?usp=drive_link",
                "alt": "no alt"
            },
            {
                "src": "https://drive.google.com/file/d/1CD2bbU5veyxl_MvHNChu32vu2briBH4D/view?usp=drive_link",
                "alt": "no alt"
            },
            {
                "src": "https://drive.google.com/file/d/1g7cug4Lrz-SL_FUF_A-nGMLp_k_j25Av/view?usp=drive_link",
                "alt": "no alt"
            },
            {
                "src": "https://drive.google.com/file/d/1wCin4Llif9Izk2Rw8Ds5jHPw0iGre4Q2/view?usp=drive_link",
                "alt": "no alt"
            },
            {
                "src": "https://drive.google.com/file/d/153shNfTFx33WTxoDdITmrUAF5KhMOgsY/view?usp=drive_link",
                "alt": "no alt"
            },
            {
                "src": "https://drive.google.com/file/d/1N34cD6pH2QzlKnM-f2wbCxBjUWTKo8Pe/view?usp=drive_link",
                "alt": "no alt"
            },
            {
                "src": "https://drive.google.com/file/d/1bJ_Lxobd35-xPeAhhNUt3tZ4Qe8INgcg/view?usp=drive_link",
                "alt": "no alt"
            },
            {
                "src": "https://drive.google.com/file/d/1JCladOIXVhFXMa4dYjKWPlOO_2Cgpe56/view?usp=drive_link",
                "alt": "no alt"
            },
            {
                "src": "https://drive.google.com/file/d/1GDMbd62b4ZsHPgUH8gHj7DMxyAzPcAAU/view?usp=drive_link",
                "alt": "no alt"
            },
            {
                "src": "https://drive.google.com/file/d/1SxvYKSG3KrmPiOmbEAfXcXpUkqPxTMA8/view?usp=drive_link",
                "alt": "no alt"
            },
            {
                "src": "https://drive.google.com/file/d/1k8BckonLk0NlAUgZBnnyQUpIpzfjrOwE/view?usp=drive_link",
                "alt": "no alt"
            },
            {
                "src": "https://drive.google.com/file/d/1bQBT-hCo0OWfEQvbsAOfE0oOteDSB1MB/view?usp=drive_link",
                "alt": "no alt"
            },
            {
                "src": "https://drive.google.com/file/d/1ND2JXp9UWhTDF_l0oJk0CW38X3-5JF-x/view?usp=drive_link",
                "alt": "no alt"
            },
            {
                "src": "https://drive.google.com/file/d/1hQ6rMFApcL3xE1NGAa82oUHIzNOpfKge/view?usp=drive_link",
                "alt": "no alt"
            },
            {
                "src": "https://drive.google.com/file/d/1v1fG8Q77Dl1vT47Bq9a_QrwCA23a4UEV/view?usp=drive_link",
                "alt": "no alt"
            },
            {
                "src": "https://drive.google.com/file/d/151KGap1KqAnnjiKIBfhSpDm5K5AXsWs0/view?usp=drive_link",
                "alt": "no alt"
            },
            {
                "src": "https://drive.google.com/file/d/1sVvwjBVMkWQuJGuhJZb0qZYCXIp1DsYN/view?usp=drive_link",
                "alt": "no alt"
            },
            {
                "src": "https://drive.google.com/file/d/1Xm90nEJc3jKeCnwfLS7xdOpr9s6IYiT7/view?usp=drive_link",
                "alt": "no alt"
            },
            {
                "src": "https://drive.google.com/file/d/1I0AxAuzXCTH5orADXmasDlgbCxQgQSQv/view?usp=drive_link",
                "alt": "no alt"
            },
            {
                "src": "https://drive.google.com/file/d/1FO7wROvQqG2liaakEffe-fCeG8Acs_8N/view?usp=drive_link",
                "alt": "no alt"
            },
            {
                "src": "https://drive.google.com/file/d/1-T8eZDEN6kAoGAdyOkljprwnKpNHAKTu/view?usp=drive_link",
                "alt": "no alt"
            },
            {
                "src": "https://drive.google.com/file/d/18oFXbDSJaumBIYSNfuSS51c8jXYENtIL/view?usp=drive_link",
                "alt": "no alt"
            },
            {
                "src": "https://drive.google.com/file/d/18ls4sbPPbapkI8dA4WEbPtEuULbVh8eQ/view?usp=drive_link",
                "alt": "no alt"
            },
            {
                "src": "https://drive.google.com/file/d/1L-uYtwYCD-sde7lU-Xe1dIK4LCL9f-X3/view?usp=drive_link",
                "alt": "no alt"
            },
            {
                "src": "https://drive.google.com/file/d/1xrEOIDnFtVuG5DBbD7AZ9AEVz7TBDJuv/view?usp=drive_link",
                "alt": "no alt"
            },
            {
                "src": "https://drive.google.com/file/d/1kCWXNMhwoewHRwHCJap_fIBFdViT4HCc/view?usp=drive_link",
                "alt": "no alt"
            },
            {
                "src": "https://drive.google.com/file/d/1PmKSJ1watTJxezXwZmnooM49ydRIdVHP/view?usp=drive_link",
                "alt": "no alt"
            },
            {
                "src": "https://drive.google.com/file/d/1N0wW3xQuaASUBk6Il5gxWjjpZwK-3X-e/view?usp=drive_link",
                "alt": "no alt"
            },
            {
                "src": "https://drive.google.com/file/d/1X7-dCtJaBf9HhLWH2qh-2reO0MHps4H9/view?usp=drive_link",
                "alt": "no alt"
            },
            {
                "src": "https://drive.google.com/file/d/17R8gH2_Mgk5FF5Dncws_eE2iPWq8VWy0/view?usp=drive_link",
                "alt": "no alt"
            },
            {
                "src": "https://drive.google.com/file/d/14hoBKz5DCqZAmPon3fKYDlG3EiCwWFdG/view?usp=drive_link",
                "alt": "no alt"
            },
            {
                "src": "https://drive.google.com/file/d/1OaROCHKmfGKu011INIJgI11qnU9jL1r5/view?usp=drive_link",
                "alt": "no alt"
            },
            {
                "src": "https://drive.google.com/file/d/10k1aXWqNP54zL5YY46Jkbnd0lMQL1dns/view?usp=drive_link",
                "alt": "no alt"
            },
            {
                "src": "https://drive.google.com/file/d/12LkwPmWQYeiOLCJCMKnoMHXKbyXiZ_X8/view?usp=drive_link",
                "alt": "no alt"
            },
            {
                "src": "https://drive.google.com/file/d/1M02E4yHQK_shVcER1qUFKXRFkJ-V2z6h/view?usp=drive_link",
                "alt": "no alt"
            },
            {
                "src": "https://drive.google.com/file/d/1ltXXh4Cuef80Z2MwoE1RyMV93F_BHElB/view?usp=drive_link",
                "alt": "no alt"
            },
            {
                "src": "https://drive.google.com/file/d/1byyiSgE-xOq4XDJHeoTXqKz87dO1dT9F/view?usp=drive_link",
                "alt": "no alt"
            },
            {
                "src": "https://drive.google.com/file/d/1wPAZFLeijtf5pokozHDDXjYcoD1-vSmY/view?usp=drive_link",
                "alt": "no alt"
            },
            {
                "src": "https://drive.google.com/file/d/1aP5P7EHUaNTfmJNU6jKwhG6sgUdQCTdV/view?usp=drive_link",
                "alt": "no alt"
            },
            {
                "src": "https://drive.google.com/file/d/1W2xRVHjD9A2uPZkqf-z3m9xWVZRQCGic/view?usp=drive_link",
                "alt": "no alt"
            },
            {
                "src": "https://drive.google.com/file/d/1ieo0bGrhLQYUn6XE1WWzXKEg2BkZB94m/view?usp=drive_link",
                "alt": "no alt"
            },
            {
                "src": "https://drive.google.com/file/d/14-jVOY5SJ-emspA43JRiIo1AoUXdgtBE/view?usp=drive_link",
                "alt": "no alt"
            },
            {
                "src": "https://drive.google.com/file/d/18S8uLzLL84FaVuuj8cZhCzzuDWtOrhKt/view?usp=drive_link",
                "alt": "no alt"
            },
            {
                "src": "https://drive.google.com/file/d/1xTV2fd8p39CnUBLWAeb3rFMN3U2-FWvd/view?usp=drive_link",
                "alt": "no alt"
            },
            {
                "src": "https://drive.google.com/file/d/1q6gtUCd6iX0t8JZQZfMnzKcsPbWJUnwE/view?usp=drive_link",
                "alt": "no alt"
            },
            {
                "src": "https://drive.google.com/file/d/1DOY7879tjen-AwPaZgVEIndQvsE2Wrts/view?usp=drive_link",
                "alt": "no alt"
            },
            {
                "src": "https://drive.google.com/file/d/15_7UKL2d3elaJs7ilhSnJMSksFz4vFCh/view?usp=drive_link",
                "alt": "no alt"
            },
            {
                "src": "https://drive.google.com/file/d/1AB_ecrmiH64SoUi5yqN5NXxHgrKKCXbs/view?usp=drive_link",
                "alt": "no alt"
            },
            {
                "src": "https://drive.google.com/file/d/1ETJzyaFHDEBF-tdRch9eYPNBqYw8_OrO/view?usp=drive_link",
                "alt": "no alt"
            },
            {
                "src": "https://drive.google.com/file/d/1j7BrTKoP6z4ias9lCSKKQ5pSncaRnr0H/view?usp=drive_link",
                "alt": "no alt"
            },
            {
                "src": "https://drive.google.com/file/d/1nHPBNVO16LZjf97yQgIeH-Ec14DvyNMV/view?usp=drive_link",
                "alt": "no alt"
            },
            {
                "src": "https://drive.google.com/file/d/17ggldzEAzq-IKBCY9FeAdgz1b8pUQicX/view?usp=drive_link",
                "alt": "no alt"
            },
            {
                "src": "https://drive.google.com/file/d/1f3e8BjJISMnhsfxQ7HSzFD97tClFXoCm/view?usp=drive_link",
                "alt": "no alt"
            },
            {
                "src": "https://drive.google.com/file/d/1npmiLPeACMmYDEzkOOxeUs5BDL0JHTAV/view?usp=drive_link",
                "alt": "no alt"
            },
            {
                "src": "https://drive.google.com/file/d/1F2jU6uU2Cxq2B_g6Bb1zDZLx31A2f6rZ/view?usp=drive_link",
                "alt": "no alt"
            },
            {
                "src": "https://drive.google.com/file/d/1n4i_RCl2ihh5Yy8JlU8lgyI4Ag6EVRKa/view?usp=drive_link",
                "alt": "no alt"
            },
            {
                "src": "https://drive.google.com/file/d/155Lv1mHBr_1H1qJQFT5GhyJGv_zgoe8z/view?usp=drive_link",
                "alt": "no alt"
            },
            {
                "src": "https://drive.google.com/file/d/1hKiueKjJmAjNhhdmSELcLdd09f4L9Dt4/view?usp=drive_link",
                "alt": "no alt"
            },
            {
                "src": "https://drive.google.com/file/d/1OLTo6QiIZmTLmRFbAr5Y-y2iRlqRsdUK/view?usp=drive_link",
                "alt": "no alt"
            },
            {
                "src": "https://drive.google.com/file/d/1K08y1NuG8i1jRM-xuJHk4Mcy5Ha64fW8/view?usp=drive_link",
                "alt": "no alt"
            },
            {
                "src": "https://drive.google.com/file/d/1JVEz1W8yglRMFrxsy82j8gINBjzojUG0/view?usp=drive_link",
                "alt": "no alt"
            },
            {
                "src": "https://drive.google.com/file/d/1n1ZmT9vbMCo9cbaJ8Owo0fmPj-4sTWsn/view?usp=drive_link",
                "alt": "no alt"
            },
            {
                "src": "https://drive.google.com/file/d/1QKO-7fYA7sbevuJy4_aZZK9bvjPSNF6X/view?usp=drive_link",
                "alt": "no alt"
            },
            {
                "src": "https://drive.google.com/file/d/1QAALLJ6VuOKSdkYBgth_Rr44gIQ3BOug/view?usp=drive_link",
                "alt": "no alt"
            },
            {
                "src": "https://drive.google.com/file/d/1gA0p3v4Mba-u2vDIGvybZcpHmafCXMO0/view?usp=drive_link",
                "alt": "no alt"
            },
            {
                "src": "https://drive.google.com/file/d/12ingwDQ3O-X_ahzDf-wD9glt59sFxZtY/view?usp=drive_link",
                "alt": "no alt"
            },
            {
                "src": "https://drive.google.com/file/d/1RYImGvgGXWqwriI-mO7jKCsyLba0R9AT/view?usp=drive_link",
                "alt": "no alt"
            },
            {
                "src": "https://drive.google.com/file/d/1PdLpi8ry_go1LhsUAOA0fc0SsPSVd1-b/view?usp=drive_link",
                "alt": "no alt"
            },
            {
                "src": "https://drive.google.com/file/d/112dcmkibelLXtK6DV-OCG8Sve9fko6Ed/view?usp=drive_link",
                "alt": "no alt"
            },
            {
                "src": "https://drive.google.com/file/d/1TQqn_itZom06rvzRAFTZCRk0nchaN583/view?usp=drive_link",
                "alt": "no alt"
            },
            {
                "src": "https://drive.google.com/file/d/1xg4z8a5s6r61PT34XRt0C1qIJPlEGSdJ/view?usp=drive_link",
                "alt": "no alt"
            },
            {
                "src": "https://drive.google.com/file/d/1T9SFaQMWU-v-UNjAMuwcAQ6w9EnJRkAI/view?usp=drive_link",
                "alt": "no alt"
            },
            {
                "src": "https://drive.google.com/file/d/1rdQj1sIB9K3EgROJvdHWHGYEn0sZNVw5/view?usp=drive_link",
                "alt": "no alt"
            },
            {
                "src": "https://drive.google.com/file/d/1MtdU6-TVrgGQ6eHhR5Tb6MM3QnuIfjms/view?usp=drive_link",
                "alt": "no alt"
            },
            {
                "src": "https://drive.google.com/file/d/1NBUPBuRYwUXEMvSEUoGhFOvhbCcnzR66/view?usp=drive_link",
                "alt": "no alt"
            },
            {
                "src": "https://drive.google.com/file/d/1LFhnua7JKOrdduHcdAaiWfSs5FJ0kyfe/view?usp=drive_link",
                "alt": "no alt"
            },
            {
                "src": "https://drive.google.com/file/d/16uGS5m8B4DGPljnK1Jc4FdSJOiIQT9k0/view?usp=drive_link",
                "alt": "no alt"
            },
            {
                "src": "https://drive.google.com/file/d/1LvWY1l5H-N_PWLy2LVdMnGt3YqRSWKPL/view?usp=drive_link",
                "alt": "no alt"
            },
            {
                "src": "https://drive.google.com/file/d/1tmOJYEGz_zael-DJnNGUQNb5KidRmcok/view?usp=drive_link",
                "alt": "no alt"
            },
            {
                "src": "https://drive.google.com/file/d/14qDsk4FTQy4G7N8SfoR-Z71C-AwMRDMf/view?usp=drive_link",
                "alt": "no alt"
            },
            {
                "src": "https://drive.google.com/file/d/1VBPbDoenV-HkT4yI797WZa-nUw4pq6fn/view?usp=drive_link",
                "alt": "no alt"
            },
            {
                "src": "https://drive.google.com/file/d/1r8Qd0LVz1N3HeEMlnaqkpAVUy5365cdh/view?usp=drive_link",
                "alt": "no alt"
            },
            {
                "src": "https://drive.google.com/file/d/1FdvhaiLYbHWKy8Rs046q7LBHqYmGlYnQ/view?usp=drive_link",
                "alt": "no alt"
            },
            {
                "src": "https://drive.google.com/file/d/1tn8Ym1BVXdYbCwnofuoR0wjlHRmaiURW/view?usp=drive_link",
                "alt": "no alt"
            },
            {
                "src": "https://drive.google.com/file/d/1LRm6Dk-K_A03B7Rbs0qRF51Pd824L1UN/view?usp=drive_link",
                "alt": "no alt"
            },
            {
                "src": "https://drive.google.com/file/d/1O3R7iNQzu1chyo9VVPasjj6el-4vWV0v/view?usp=drive_link",
                "alt": "no alt"
            },
            {
                "src": "https://drive.google.com/file/d/1YSRSuOpiP-ni_AdNWlFMRC3sv5C5Q683/view?usp=drive_link",
                "alt": "no alt"
            },
            {
                "src": "https://drive.google.com/file/d/15ETFREC-cCtIH_0TaDdNtOiUdUKv1uPj/view?usp=drive_link",
                "alt": "no alt"
            },
            {
                "src": "https://drive.google.com/file/d/1yEvlyXsA2qUiftoQslp70SAOpBqI5XY8/view?usp=drive_link",
                "alt": "no alt"
            },
            {
                "src": "https://drive.google.com/file/d/1vcQYVq91sU68r-dOdkCpQAP2yZpA44Mf/view?usp=drive_link",
                "alt": "no alt"
            },
            {
                "src": "https://drive.google.com/file/d/1QKeEgSpKbGT16sYLYfefByzdK7xIGQh2/view?usp=drive_link",
                "alt": "no alt"
            },
            {
                "src": "https://drive.google.com/file/d/1b7BHSO1Yv9ctV0-vcWdRi9roP1ekJl0J/view?usp=drive_link",
                "alt": "no alt"
            },
            {
                "src": "https://drive.google.com/file/d/1LTdCu06IaclMpNBJodnXP6BOCkgnVVG_/view?usp=drive_link",
                "alt": "no alt"
            },
            {
                "src": "https://drive.google.com/file/d/1hvhoJzFIcUnW43kl482S4R6fs8K7PWNr/view?usp=drive_link",
                "alt": "no alt"
            },
            {
                "src": "https://drive.google.com/file/d/1TpdmQ9E_A3OjAJ0WLp7jYp1YHhTSpzul/view?usp=drive_link",
                "alt": "no alt"
            },
            {
                "src": "https://drive.google.com/file/d/1Oxn8vCnn-NwEES_ASRVC_kh-UPzYU7eK/view?usp=drive_link",
                "alt": "no alt"
            },
            {
                "src": "https://drive.google.com/file/d/1oV6P3hPWeFkjV8fTxx8Q5P45KJUOTSlF/view?usp=drive_link",
                "alt": "no alt"
            },
            {
                "src": "https://drive.google.com/file/d/1_pzbvoT1t_KB4IG4TWJtxalm8iCHoi3Z/view?usp=drive_link",
                "alt": "no alt"
            },
            {
                "src": "https://drive.google.com/file/d/1T60EIvM16puUdlO6DGB-MGgot3c0sBpr/view?usp=drive_link",
                "alt": "no alt"
            },
            {
                "src": "https://drive.google.com/file/d/1aV9r1uJ35DYgT-nvk33eqxIxp5sAw_aL/view?usp=drive_link",
                "alt": "no alt"
            },
            {
                "src": "https://drive.google.com/file/d/1avGnXpTfrWZBKR9fRO5ZMgNR_5F3zmfe/view?usp=drive_link",
                "alt": "no alt"
            },
            {
                "src": "https://drive.google.com/file/d/1aJSY7RTV7GJHoqeGM8iXEDJkwpnTDiTK/view?usp=drive_link",
                "alt": "no alt"
            },
            {
                "src": "https://drive.google.com/file/d/16p28VG75E1H1yEjDZgv2xUldyzpmxjyP/view?usp=drive_link",
                "alt": "no alt"
            },
            {
                "src": "https://drive.google.com/file/d/1heVUwb8tTKATehkSXg5kPxxfNCpokiex/view?usp=drive_link",
                "alt": "no alt"
            },
            {
                "src": "https://drive.google.com/file/d/1Xok8cBUdbTj3LxfXKnXIph2ObaGSWnEc/view?usp=drive_link",
                "alt": "no alt"
            },
            {
                "src": "https://drive.google.com/file/d/11f-RNyLcvwOLJ3tAiB00NsFfzY5WLzGI/view?usp=drive_link",
                "alt": "no alt"
            },
            {
                "src": "https://drive.google.com/file/d/1rNuxIvFMJ-BbUdqfv8Uh82rggHd4GqdS/view?usp=drive_link",
                "alt": "no alt"
            },
            {
                "src": "https://drive.google.com/file/d/1GE0PpuxkDrQfHc6XwswfdlCw1jk3sunc/view?usp=drive_link",
                "alt": "no alt"
            },
            {
                "src": "https://drive.google.com/file/d/1i2dXPRnkeZkpjNYbdpuxynGJ8YIGFgu2/view?usp=drive_link",
                "alt": "no alt"
            },
            {
                "src": "https://drive.google.com/file/d/129e-bIV3ehaSaSmyWpJSxuQg0to9NxLU/view?usp=drive_link",
                "alt": "no alt"
            },
            {
                "src": "https://drive.google.com/file/d/1Zf86ixegYchifIVjBLH6ihGaZo960FM-/view?usp=drive_link",
                "alt": "no alt"
            },
            {
                "src": "https://drive.google.com/file/d/1FHNpvymbvJSrEtjs1n44ZXdWEoB31RPo/view?usp=drive_link",
                "alt": "no alt"
            },
            {
                "src": "https://drive.google.com/file/d/12hXzWNiOgz6IwClRGuGzYh4ITFmnnWuO/view?usp=drive_link",
                "alt": "no alt"
            },
            {
                "src": "https://drive.google.com/file/d/1joGTGCL81n5rn3VUQIMumAUGu_VkLyon/view?usp=drive_link",
                "alt": "no alt"
            },
            {
                "src": "https://drive.google.com/file/d/1tq7bh2X5GzHApvuAPFasmxwd1iuifmYC/view?usp=drive_link",
                "alt": "no alt"
            },
            {
                "src": "https://drive.google.com/file/d/1ijHtO_jRkmSBIE-wVhsnoJyOZYnDBQc0/view?usp=drive_link",
                "alt": "no alt"
            },
            {
                "src": "https://drive.google.com/file/d/1_SmXQ2PyctFSZH5mxhgqmS0omAyn3GG-/view?usp=drive_link",
                "alt": "no alt"
            },
            {
                "src": "https://drive.google.com/file/d/1j0BDDjySdsiJKDt6Va0NUwhYA3zntlAR/view?usp=drive_link",
                "alt": "no alt"
            },
            {
                "src": "https://drive.google.com/file/d/1RfPrjn1F2fPpe4cbl2jEOLoMjZLVl4op/view?usp=drive_link",
                "alt": "no alt"
            },
            {
                "src": "https://drive.google.com/file/d/1YHw6h0WAZLcEWZVlpMh7CgI9ET80YF9Y/view?usp=drive_link",
                "alt": "no alt"
            },
            {
                "src": "https://drive.google.com/file/d/1AXYjrRr5CqH9ilogVnxfXDUxzpYZhF8F/view?usp=drive_link",
                "alt": "no alt"
            },
            {
                "src": "https://drive.google.com/file/d/1vcoYnu4IiXbtvgBYGJNSCMwmXep-b5H0/view?usp=drive_link",
                "alt": "no alt"
            },
            {
                "src": "https://drive.google.com/file/d/1ZsIRrjf9PB5j3XFfjG4Qt2un086R9vH9/view?usp=drive_link",
                "alt": "no alt"
            },
            {
                "src": "https://drive.google.com/file/d/19LRRQK5JQsLA4lYIfXgUfbKNZVa-vIyH/view?usp=drive_link",
                "alt": "no alt"
            },
            {
                "src": "https://drive.google.com/file/d/1CTD7yy93BPBLyDe_HCiMtT-VE9Dew099/view?usp=drive_link",
                "alt": "no alt"
            },
            {
                "src": "https://drive.google.com/file/d/1YQoIsH2eZ4uePdh0xX38TC-UnjHKGHG8/view?usp=drive_link",
                "alt": "no alt"
            },
            {
                "src": "https://drive.google.com/file/d/1qsddy0BugfbU7uMwQPxX5ylhNhyTeLHR/view?usp=drive_link",
                "alt": "no alt"
            },
            {
                "src": "https://drive.google.com/file/d/14fDUoZMGJIp72rZBQHE0814XmMX2p_rm/view?usp=drive_link",
                "alt": "no alt"
            },
            {
                "src": "https://drive.google.com/file/d/10y0vpdq1zHRgBPmsCqQ-dwMbftrwQIgV/view?usp=drive_link",
                "alt": "no alt"
            },
            {
                "src": "https://drive.google.com/file/d/1XY3SuM6DnF0iI6JtBeoNavwU2Lpyiguc/view?usp=drive_link",
                "alt": "no alt"
            },
            {
                "src": "https://drive.google.com/file/d/1ipGUfpnYt-7VKQjIA-JqjLej0Pb8mdLs/view?usp=drive_link",
                "alt": "no alt"
            },
            {
                "src": "https://drive.google.com/file/d/16lr7bQfTAYlUr6z7EamYHSrmi6ZTuYxN/view?usp=drive_link",
                "alt": "no alt"
            },
            {
                "src": "https://drive.google.com/file/d/1wEgn854HeJKI2kloK3vXsSzhwFW0ITzT/view?usp=drive_link",
                "alt": "no alt"
            },
            {
                "src": "https://drive.google.com/file/d/1SayjmNwUn8vySgkrV09BjDptedhHY-rc/view?usp=drive_link",
                "alt": "no alt"
            },
            {
                "src": "https://drive.google.com/file/d/1xTCVPBLIAmWVNybQAR8qwzBnbrF0vZOL/view?usp=drive_link",
                "alt": "no alt"
            },
            {
                "src": "https://drive.google.com/file/d/14U1FCwSNNb0L79wnXTVn2H1kJRIS9LXG/view?usp=drive_link",
                "alt": "no alt"
            },
            {
                "src": "https://drive.google.com/file/d/1KfZSIrYgvvwgE_Lgj4j-05hHmbYp8jEQ/view?usp=drive_link",
                "alt": "no alt"
            },
            {
                "src": "https://drive.google.com/file/d/194Lm5tAuIjoHv1JUfWwsMIDL8UqpucpJ/view?usp=drive_link",
                "alt": "no alt"
            },
            {
                "src": "https://drive.google.com/file/d/1CEJG2rFQiG7X00HTvjdIWhqGMEweD0_W/view?usp=drive_link",
                "alt": "no alt"
            },
            {
                "src": "https://drive.google.com/file/d/1Ri6521YwvZfTSd8s0RC0mTWOUYqlzTdX/view?usp=drive_link",
                "alt": "no alt"
            },
            {
                "src": "https://drive.google.com/file/d/1v2ni9Ewt67LOXKjtOuL_tQYMjUxAy74M/view?usp=drive_link",
                "alt": "no alt"
            },
            {
                "src": "https://drive.google.com/file/d/1id6TRU3XNES1shxPStNJgv3hQGyaPckR/view?usp=drive_link",
                "alt": "no alt"
            },
            {
                "src": "https://drive.google.com/file/d/1t7_n0fXYYgpj7hbRMhszziGHm9ec1DTc/view?usp=drive_link",
                "alt": "no alt"
            },
            {
                "src": "https://drive.google.com/file/d/1Wze64gP-dVmp7ZUsloQSYsDrfCeGQTqU/view?usp=drive_link",
                "alt": "no alt"
            },
            {
                "src": "https://drive.google.com/file/d/17txZzGZZMfN72kH0VtWgZLGszHfb35Fq/view?usp=drive_link",
                "alt": "no alt"
            },
            {
                "src": "https://drive.google.com/file/d/1dYCjNnb9WPYasHI8Ir1SRyEWmy-0Ckg6/view?usp=drive_link",
                "alt": "no alt"
            },
            {
                "src": "https://drive.google.com/file/d/1Ap44HnK2N0U4bEDhQLZgA7IsePmj04BJ/view?usp=drive_link",
                "alt": "no alt"
            },
            {
                "src": "https://drive.google.com/file/d/11OL8-SI4cY8Kdb4CdBSpxvhQ7WUvXF2A/view?usp=drive_link",
                "alt": "no alt"
            },
            {
                "src": "https://drive.google.com/file/d/1Rzje8Cwawqb0Y8S87XAO4qEgv3XmjPae/view?usp=drive_link",
                "alt": "no alt"
            },
            {
                "src": "https://drive.google.com/file/d/1EldiFpvxRVzjZAsaBM1nOpiyCfi5UTm7/view?usp=drive_link",
                "alt": "no alt"
            },
            {
                "src": "https://drive.google.com/file/d/16cWRBM_q9JQ5o8CIkQXBMJKFALwW740a/view?usp=drive_link",
                "alt": "no alt"
            },
            {
                "src": "https://drive.google.com/file/d/1WPAKq9wOTP98M5BYG5uQhOYR0TOZmNt_/view?usp=drive_link",
                "alt": "no alt"
            },
            {
                "src": "https://drive.google.com/file/d/1poSVUgWIAFnVGjUcjISH9zowHxzdDRy9/view?usp=drive_link",
                "alt": "no alt"
            },
            {
                "src": "https://drive.google.com/file/d/1CRIh6WYzt2zkS0Y-9utOEWG_W9KebPNU/view?usp=drive_link",
                "alt": "no alt"
            },
            {
                "src": "https://drive.google.com/file/d/13hciiYWGfR79uBBkWdnQ9LL0WMxbCnpT/view?usp=drive_link",
                "alt": "no alt"
            },
            {
                "src": "https://drive.google.com/file/d/1z4bYy2FJrrq1Pw693bA8Wk3F72GEq_Oz/view?usp=drive_link",
                "alt": "no alt"
            },
            {
                "src": "https://drive.google.com/file/d/1bzI8H-WKmXp8bdInC17jneg9HfvHd1Z3/view?usp=drive_link",
                "alt": "no alt"
            },
            {
                "src": "https://drive.google.com/file/d/1iOEi749HlT9sg4XKAtsL0OVYbTACom0Z/view?usp=drive_link",
                "alt": "no alt"
            },
            {
                "src": "https://drive.google.com/file/d/1X9Yp1HMKddvYwKZgrZr18xwE_d-O7uL5/view?usp=drive_link",
                "alt": "no alt"
            },
            {
                "src": "https://drive.google.com/file/d/1StmIQ_FmXOgkrMXqk_et9eIAVXnZfNWw/view?usp=drive_link",
                "alt": "no alt"
            },
            {
                "src": "https://drive.google.com/file/d/1n3QdO20I0Xn5UD1p-TDkT3nnxupNL8tC/view?usp=drive_link",
                "alt": "no alt"
            },
            {
                "src": "https://drive.google.com/file/d/1tDADybaKXav6BHfQwuvZmzYyAEKxUhiF/view?usp=drive_link",
                "alt": "no alt"
            },
            {
                "src": "https://drive.google.com/file/d/1ZoZW3uikSLiEWOD88b29TyMK7l9KZaXb/view?usp=drive_link",
                "alt": "no alt"
            },
            {
                "src": "https://drive.google.com/file/d/1VZRaKc2W3fqy8AvBIjCmRqOZb4ajCWHb/view?usp=drive_link",
                "alt": "no alt"
            },
            {
                "src": "https://drive.google.com/file/d/1x5m5VR93IihmLcGIfro9wdB9QswUk8rI/view?usp=drive_link",
                "alt": "no alt"
            },
            {
                "src": "https://drive.google.com/file/d/1rwMYMkOaAE04dT8Fj3mr7aRGBd2pjvsm/view?usp=drive_link",
                "alt": "no alt"
            },
            {
                "src": "https://drive.google.com/file/d/1WOQ0AKo3aeOKvL4ouuKlIfuY3ZZLiynd/view?usp=drive_link",
                "alt": "no alt"
            },
            {
                "src": "https://drive.google.com/file/d/1q2aqtcNrIZjZLQHvYV-PXGOOKbI0C-Kl/view?usp=drive_link",
                "alt": "no alt"
            },
            {
                "src": "https://drive.google.com/file/d/1W5lRKezGUgvQD2N0lLTtVFA0Z2m0R9Yg/view?usp=drive_link",
                "alt": "no alt"
            },
            {
                "src": "https://drive.google.com/file/d/1STPJ2ckTh1l7FUqzUHoDm3rjzJYtm3f1/view?usp=drive_link",
                "alt": "no alt"
            },
            {
                "src": "https://drive.google.com/file/d/1yMsDsfbGzR9XOUlINRoKszJ-WHcm-uMb/view?usp=drive_link",
                "alt": "no alt"
            },
            {
                "src": "https://drive.google.com/file/d/1J1l_PujZRBie42wz-9yG2nirUKNZfTcp/view?usp=drive_link",
                "alt": "no alt"
            },
            {
                "src": "https://drive.google.com/file/d/1T_G1bQlcLOXC-NHKGGJjRkTPaeE8dy06/view?usp=drive_link",
                "alt": "no alt"
            },
            {
                "src": "https://drive.google.com/file/d/1lpbN9JEPBu2bW3GaFyerTQIn9UfFXO4G/view?usp=drive_link",
                "alt": "no alt"
            },
            {
                "src": "https://drive.google.com/file/d/14qlcYgFYhDEAXzty1Rm3WUutaxNKm7hw/view?usp=drive_link",
                "alt": "no alt"
            },
            {
                "src": "https://drive.google.com/file/d/1Zy1-DjHhXDMHKGgn0rEOrxh7DBu0oYU-/view?usp=drive_link",
                "alt": "no alt"
            },
            {
                "src": "https://drive.google.com/file/d/1u2n6d1i5Sra7rsLQMrrb4MiicM6M94gD/view?usp=drive_link",
                "alt": "no alt"
            },
            {
                "src": "https://drive.google.com/file/d/1r8fasbrKERPd4T4PKNabccgdQj2IPTsM/view?usp=drive_link",
                "alt": "no alt"
            },
            {
                "src": "https://drive.google.com/file/d/1lay_8zuTw70_gU5aESzFvUeE69K51qOR/view?usp=drive_link",
                "alt": "no alt"
            },
            {
                "src": "https://drive.google.com/file/d/1UFTIDegGHOO16SSL2TMPg1a3zGE_zcS1/view?usp=drive_link",
                "alt": "no alt"
            },
            {
                "src": "https://drive.google.com/file/d/1rGZIJDh76y43NVIxgTFX5yM_n_wOo1Ig/view?usp=drive_link",
                "alt": "no alt"
            },
            {
                "src": "https://drive.google.com/file/d/1s6amJw5HfmIA0Pcm2Z9-YetMz0BOPhNn/view?usp=drive_link",
                "alt": "no alt"
            },
            {
                "src": "https://drive.google.com/file/d/1KiPeZvppK7O_yoBu9Qn8evSujOKtqDD_/view?usp=drive_link",
                "alt": "no alt"
            },
            {
                "src": "https://drive.google.com/file/d/1Hw6R9mLRdrYX40Oy8KKjG_PVN_EoJpOX/view?usp=drive_link",
                "alt": "no alt"
            },
            {
                "src": "https://drive.google.com/file/d/1XGjvpZpOi5W9zG0YCMAlIBqd81_1M-Wy/view?usp=drive_link",
                "alt": "no alt"
            },
            {
                "src": "https://drive.google.com/file/d/1ToWhE5Sf5ImreSBpzDnQRfdwv0z3uVyq/view?usp=drive_link",
                "alt": "no alt"
            },
            {
                "src": "https://drive.google.com/file/d/1rVwdS2bELE8FWWNoPKJ8NikG6glIHWK3/view?usp=drive_link",
                "alt": "no alt"
            },
            {
                "src": "https://drive.google.com/file/d/1lGsNeYZiZcdffMZjJqXmwROgD3b3p_sX/view?usp=drive_link",
                "alt": "no alt"
            },
            {
                "src": "https://drive.google.com/file/d/1n3HKw5oawYtzJprROwJkTS89Hmqs9vrk/view?usp=drive_link",
                "alt": "no alt"
            },
            {
                "src": "https://drive.google.com/file/d/1qGE1qc6BhejGBja7CxTJCORoXPqrYAEz/view?usp=drive_link",
                "alt": "no alt"
            },
            {
                "src": "https://drive.google.com/file/d/1ez4i2udt5IcRVZ8KP_R-KK2giCda1ZCD/view?usp=drive_link",
                "alt": "no alt"
            },
            {
                "src": "https://drive.google.com/file/d/1AjYkgYYf-JUfL4y1CaoGgGN3-qrlYG5J/view?usp=drive_link",
                "alt": "no alt"
            },
            {
                "src": "https://drive.google.com/file/d/1IhsOATXqYr4yNLRrFQAWBNY9_ofUr_qk/view?usp=drive_link",
                "alt": "no alt"
            },
            {
                "src": "https://drive.google.com/file/d/1-hesELd45tYfOuRdbe5zb6S9fR15XNg8/view?usp=drive_link",
                "alt": "no alt"
            },
            {
                "src": "https://drive.google.com/file/d/15SWet5OGl2CHYsLCRGZtY9Qh50ElVDzu/view?usp=drive_link",
                "alt": "no alt"
            },
            {
                "src": "https://drive.google.com/file/d/1LHllukxLBBlsDUWBeDUyPfbg2Ili6sTa/view?usp=drive_link",
                "alt": "no alt"
            },
            {
                "src": "https://drive.google.com/file/d/1WaMueuyIg520vBiuSqeDeOVRGaQ1mk-G/view?usp=drive_link",
                "alt": "no alt"
            },
            {
                "src": "https://drive.google.com/file/d/1Ymd58BwL4TEQE_i4hZPM12rR5TRaPGcI/view?usp=drive_link",
                "alt": "no alt"
            },
            {
                "src": "https://drive.google.com/file/d/1MUOL9Gdj-OX6KeMx7gPGZYdsx-s06Yxg/view?usp=drive_link",
                "alt": "no alt"
            },
            {
                "src": "https://drive.google.com/file/d/17Moadhlonh9mBsQ4tHzmelvRWPHRFl4a/view?usp=drive_link",
                "alt": "no alt"
            },
            {
                "src": "https://drive.google.com/file/d/1fZif_nxJ7vqAGeK5Q8pb2NyEz3km8-ZF/view?usp=drive_link",
                "alt": "no alt"
            },
            {
                "src": "https://drive.google.com/file/d/1CqUOSvLVaBX_EbJ6RMdQg4uDKRkckrDO/view?usp=drive_link",
                "alt": "no alt"
            },
            {
                "src": "https://drive.google.com/file/d/1DURwrgs1rneXzEn0RA4u7Yk-SF8wAjf3/view?usp=drive_link",
                "alt": "no alt"
            },
            {
                "src": "https://drive.google.com/file/d/1FXB0mvlQyQeq4kgozW2M7gXlZg3zkJGK/view?usp=drive_link",
                "alt": "no alt"
            },
            {
                "src": "https://drive.google.com/file/d/1WvRHqANutb6Gf2khej0mnCqCzlEgy6Un/view?usp=drive_link",
                "alt": "no alt"
            },
            {
                "src": "https://drive.google.com/file/d/1vMlvqaTAStG5jSzHO8mddHrSlkOkmAov/view?usp=drive_link",
                "alt": "no alt"
            },
            {
                "src": "https://drive.google.com/file/d/1fFTUzEasW09CqpLwKSuuSqxMWCyqHKSu/view?usp=drive_link",
                "alt": "no alt"
            },
            {
                "src": "https://drive.google.com/file/d/1Hpak8TDIbmHayEtQNkm4wizuDa4EuenO/view?usp=drive_link",
                "alt": "no alt"
            },
            {
                "src": "https://drive.google.com/file/d/1gYGwsemlh0VgoawleHncGCaQSNb_WdUb/view?usp=drive_link",
                "alt": "no alt"
            },
            {
                "src": "https://drive.google.com/file/d/1vhSyWN-G2B64rY3lE-nlhWEpbS1rCDR3/view?usp=drive_link",
                "alt": "no alt"
            },
            {
                "src": "https://drive.google.com/file/d/1G4CAJRaDqIw7qlUizjFuvzSdgBWMkqXo/view?usp=drive_link",
                "alt": "no alt"
            },
            {
                "src": "https://drive.google.com/file/d/1S0n1viYb981XueDMEN06426QIxRkojFb/view?usp=drive_link",
                "alt": "no alt"
            },
            {
                "src": "https://drive.google.com/file/d/1XPWd-EBo6cqs6o2XYm7FRac08T3grCCf/view?usp=drive_link",
                "alt": "no alt"
            },
            {
                "src": "https://drive.google.com/file/d/1k52rCzVt3XFj9xtW-TIOYGPZiRx6S28p/view?usp=drive_link",
                "alt": "no alt"
            },
            {
                "src": "https://drive.google.com/file/d/1qy69kNODzuDXhJ4WA-0V4X_0xvGfmPp0/view?usp=drive_link",
                "alt": "no alt"
            },
            {
                "src": "https://drive.google.com/file/d/1if0ij-Orso8ktYjNEv53b1BTO2lDrj6g/view?usp=drive_link",
                "alt": "no alt"
            },
            {
                "src": "https://drive.google.com/file/d/1jTLgNbI7BrIpm4weh0fgP2dUCzh0I1JN/view?usp=drive_link",
                "alt": "no alt"
            },
            {
                "src": "https://drive.google.com/file/d/1q5dIEWjLSklGByAY0TLweymSNUZjIZ9H/view?usp=drive_link",
                "alt": "no alt"
            },
            {
                "src": "https://drive.google.com/file/d/1DPLR1_lz8ZXl-BgNFQkJnsmMRurd7Gjo/view?usp=drive_link",
                "alt": "no alt"
            },
            {
                "src": "https://drive.google.com/file/d/19RxKglVPYJSfFZbv5qcSmBJPJuCfWmV1/view?usp=drive_link",
                "alt": "no alt"
            },
            {
                "src": "https://drive.google.com/file/d/1bOokqfXsXShwl_QOVaa445sHFx2uzXR5/view?usp=drive_link",
                "alt": "no alt"
            },
            {
                "src": "https://drive.google.com/file/d/1aYueNQJLocGP3Mt-VJF_9_liewyFC39C/view?usp=drive_link",
                "alt": "no alt"
            },
            {
                "src": "https://drive.google.com/file/d/17Nhvw7qiPMfpE49VQjZxLWOyYw8mj2nh/view?usp=drive_link",
                "alt": "no alt"
            },
            {
                "src": "https://drive.google.com/file/d/18l5r8cXfhKOGhnf-EMp6dcGktsCzTf93/view?usp=drive_link",
                "alt": "no alt"
            },
            {
                "src": "https://drive.google.com/file/d/1KPGtm6qqmjZjgFYAKqppOf6PIMCjhceR/view?usp=drive_link",
                "alt": "no alt"
            },
            {
                "src": "https://drive.google.com/file/d/1uxF5I4thrVvel43gkq6yimc1SawCvl40/view?usp=drive_link",
                "alt": "no alt"
            },
            {
                "src": "https://drive.google.com/file/d/1ZsfRI9lIPt_2W1fNmLv0Jp8mxZBvjZjR/view?usp=drive_link",
                "alt": "no alt"
            },
            {
                "src": "https://drive.google.com/file/d/1rO0seUShrN6zjc_QGIJ-3jbEt19cMHpe/view?usp=drive_link",
                "alt": "no alt"
            },
            {
                "src": "https://drive.google.com/file/d/1W5IP7H927z3OaFDI8DuHItKmSfRNZsMy/view?usp=drive_link",
                "alt": "no alt"
            },
            {
                "src": "https://drive.google.com/file/d/18NrcYPH8rlxnclJHQNQQ9wYpSRZtds73/view?usp=drive_link",
                "alt": "no alt"
            },
            {
                "src": "https://drive.google.com/file/d/12tDAAzgiq559dh97rexxuLIcwoAouFGn/view?usp=drive_link",
                "alt": "no alt"
            },
            {
                "src": "https://drive.google.com/file/d/1WzEHGbHBId3jnt-yq2BMBlzjLPMb5p5T/view?usp=drive_link",
                "alt": "no alt"
            },
            {
                "src": "https://drive.google.com/file/d/1GB4_Lpjnl2PiuXnyjDohjXR9FZUJOvHa/view?usp=drive_link",
                "alt": "no alt"
            },
            {
                "src": "https://drive.google.com/file/d/10oANWSM1VZXYFyi_we8iM1tW9Tr1NJJT/view?usp=drive_link",
                "alt": "no alt"
            },
            {
                "src": "https://drive.google.com/file/d/1AE0LmDFNjMt0s08AD6_G_7vpz730sxlE/view?usp=drive_link",
                "alt": "no alt"
            },
            {
                "src": "https://drive.google.com/file/d/103ryGQwRt7bn0ovDV8Tcp8-VMZ_f6Ygm/view?usp=drive_link",
                "alt": "no alt"
            },
            {
                "src": "https://drive.google.com/file/d/1KOEQ4hpmG85B3PxS0uomCZVeYxmDDN7o/view?usp=drive_link",
                "alt": "no alt"
            },
            {
                "src": "https://drive.google.com/file/d/1GlHo3cnetXW_nn3k2ufFZI0GveuNFkt-/view?usp=drive_link",
                "alt": "no alt"
            },
            {
                "src": "https://drive.google.com/file/d/1TKD1T6pcyHXYe91eEoVal9o_OOupUaYA/view?usp=drive_link",
                "alt": "no alt"
            }
        ]
    }
}